{
    "succeed":"true",
    "list":[
        {
            "id":5,
            "title":"村上春树语录：没有人喜欢孤独，只是不愿失望",
            "detail": "你要做一个不动声色的大人了。不准情绪化，不准偷偷想念，不准回头看。去过自己另外的生活。你要听话，不是所有的鱼都会生活在同一片海里。-- 村上春...",
            "imgUrl":"/images/9073718-961643f4ce827225.jpg",
            "ad": false,
            "diamond": 64.6,
            "authorName": "发条橙skr",
            "authorId": "1",
            "commentsNumber": 631,
            "commentsUrl": "/detail/1#comments",
            "supportNumber":1956,
            "reward":5
        },
        {
            "id":6,
            "title":"为什么被你们吹爆了的《哪吒》，我只看到了满屏的尴尬？",
            "detail": "昨天我看了个动画片。片子讲的是一个村里有个小孩子自出生起体内就封印了一股强大的妖力，于是村民们把他当做妖怪，畏惧他，疏远他，避之唯恐不及。他表面...",
            "imgUrl":"images/12081621-b05fe51264d22dcb.jpg",
            "ad": false,
            "diamond": 486.5,
            "authorName": "雨天_稻草人",
            "authorId": "2",
            "commentsNumber": 2003,
            "commentsUrl": "/detail/2#comments",
            "supportNumber":3246,
            "reward":13
        },
        {
            "id":7,
            "title":"终于找到杨紫演什么火什么，ab演什么扑什么的原因",
            "detail": "要问谁是今年新晋的锦鲤女神，那肯定非杨紫莫属。 有她在的地方，先是火了《亲爱的，热爱的》，“现男友”成为七月爆款。 后来的《中餐厅》也一改前几季...",
            "imgUrl":"",
            "ad": false,
            "diamond": 118.3,
            "authorName": "花痴女王",
            "authorId": "3",
            "commentsNumber": 116,
            "commentsUrl": "/detail/3#comments",
            "supportNumber":835,
            "reward":0
        },
        {
            "id":8,
            "title":"【企业福利】买云产品送华为P40 Pro",
            "detail": "【618钜惠】30+华为云产品1折起，价值6600元红包送不停",
            "imgUrl":"images/image.jfif",
            "ad": true,
            "diamond": "",
            "authorName": "",
            "authorId": "3",
            "commentsNumber": "",
            "commentsUrl": "/detail/3#comments",
            "supportNumber":"",
            "reward":0
        }
    ]
}